{
  "Logistic Regression": {
    "accuracy": 0.6098,
    "precision": 0.0,
    "recall": 0.0,
    "f1_score": 0.0,
    "roc_auc": 0.5535,
    "confusion_matrix": [
      [
        400,
        0
      ],
      [
        256,
        0
      ]
    ]
  },
  "Decision Tree": {
    "accuracy": 0.7576,
    "precision": 0.7462,
    "recall": 0.5742,
    "f1_score": 0.649,
    "roc_auc": 0.8193,
    "confusion_matrix": [
      [
        350,
        50
      ],
      [
        109,
        147
      ]
    ]
  },
  "Random Forest": {
    "accuracy": 0.7988,
    "precision": 0.8163,
    "recall": 0.625,
    "f1_score": 0.708,
    "roc_auc": 0.8842,
    "confusion_matrix": [
      [
        364,
        36
      ],
      [
        96,
        160
      ]
    ]
  }
}